dory/__init__.py
dory/auto_instrument.py
dory/decorators.py
dory/py.typed
dory/simple.py
dory/types.py
dory/cli/__init__.py
dory/cli/main.py
dory/cli/templates.py
dory/config/__init__.py
dory/config/defaults.py
dory/config/loader.py
dory/config/presets.py
dory/config/schema.py
dory/core/__init__.py
dory/core/app.py
dory/core/context.py
dory/core/lifecycle.py
dory/core/meta.py
dory/core/modes.py
dory/core/processor.py
dory/core/signals.py
dory/errors/__init__.py
dory/errors/classification.py
dory/errors/codes.py
dory/health/__init__.py
dory/health/probes.py
dory/health/server.py
dory/k8s/__init__.py
dory/k8s/annotation_watcher.py
dory/k8s/client.py
dory/k8s/pod_metadata.py
dory/logging/__init__.py
dory/logging/logger.py
dory/metrics/__init__.py
dory/metrics/collector.py
dory/middleware/__init__.py
dory/middleware/connection_tracker.py
dory/middleware/request_id.py
dory/middleware/request_tracker.py
dory/migration/__init__.py
dory/migration/configmap.py
dory/migration/serialization.py
dory/migration/state_manager.py
dory/monitoring/__init__.py
dory/monitoring/opentelemetry.py
dory/recovery/__init__.py
dory/recovery/golden_image.py
dory/recovery/golden_snapshot.py
dory/recovery/golden_validator.py
dory/recovery/partial_recovery.py
dory/recovery/recovery_decision.py
dory/recovery/restart_detector.py
dory/recovery/state_validator.py
dory/resilience/__init__.py
dory/resilience/circuit_breaker.py
dory/resilience/retry.py
dory/utils/__init__.py
dory/utils/errors.py
dory/utils/retry.py
dory/utils/timeout.py
dory_sdk-2.1.3.dist-info/METADATA
dory_sdk-2.1.3.dist-info/WHEEL
dory_sdk-2.1.3.dist-info/entry_points.txt
dory_sdk-2.1.3.dist-info/top_level.txt
dory_sdk-2.1.3.dist-info/RECORD
