Metadata-Version: 2.4
Name: dory-sdk
Version: 2.1.3
Summary: Python SDK for building stateful processors with zero-downtime migration, auto-initialization, and smart instrumentation
Author-email: Dory Team <dory@example.com>
License: Apache-2.0
Project-URL: Homepage, https://github.com/example/dory-sdk
Project-URL: Documentation, https://dory-sdk.readthedocs.io
Project-URL: Repository, https://github.com/example/dory-sdk
Project-URL: Issues, https://github.com/example/dory-sdk/issues
Keywords: kubernetes,stateful,migration,orchestration,sdk
Classifier: Development Status :: 4 - Beta
Classifier: Intended Audience :: Developers
Classifier: License :: OSI Approved :: Apache Software License
Classifier: Operating System :: OS Independent
Classifier: Programming Language :: Python :: 3
Classifier: Programming Language :: Python :: 3.10
Classifier: Programming Language :: Python :: 3.11
Classifier: Programming Language :: Python :: 3.12
Classifier: Topic :: Software Development :: Libraries :: Python Modules
Classifier: Topic :: System :: Distributed Computing
Classifier: Typing :: Typed
Requires-Python: >=3.10
Requires-Dist: aiohttp>=3.8.0
Requires-Dist: pydantic>=2.0.0
Requires-Dist: PyYAML>=6.0
Provides-Extra: kubernetes
Requires-Dist: kubernetes>=28.0.0; extra == "kubernetes"
Provides-Extra: s3
Requires-Dist: boto3>=1.28.0; extra == "s3"
Provides-Extra: tracing
Requires-Dist: opentelemetry-api>=1.20.0; extra == "tracing"
Requires-Dist: opentelemetry-sdk>=1.20.0; extra == "tracing"
Requires-Dist: opentelemetry-exporter-otlp-proto-grpc>=1.20.0; extra == "tracing"
Provides-Extra: resilience
Provides-Extra: monitoring
Provides-Extra: dev
Requires-Dist: pytest>=7.0.0; extra == "dev"
Requires-Dist: pytest-asyncio>=0.21.0; extra == "dev"
Requires-Dist: pytest-cov>=4.0.0; extra == "dev"
Requires-Dist: mypy>=1.0.0; extra == "dev"
Requires-Dist: ruff>=0.1.0; extra == "dev"
Requires-Dist: black>=23.0.0; extra == "dev"
Provides-Extra: production
Requires-Dist: kubernetes>=28.0.0; extra == "production"
Requires-Dist: opentelemetry-api>=1.20.0; extra == "production"
Requires-Dist: opentelemetry-sdk>=1.20.0; extra == "production"
Requires-Dist: opentelemetry-exporter-otlp-proto-grpc>=1.20.0; extra == "production"
Provides-Extra: all
Requires-Dist: kubernetes>=28.0.0; extra == "all"
Requires-Dist: boto3>=1.28.0; extra == "all"
Requires-Dist: opentelemetry-api>=1.20.0; extra == "all"
Requires-Dist: opentelemetry-sdk>=1.20.0; extra == "all"
Requires-Dist: opentelemetry-exporter-otlp-proto-grpc>=1.20.0; extra == "all"
Requires-Dist: pytest>=7.0.0; extra == "all"
Requires-Dist: pytest-asyncio>=0.21.0; extra == "all"
Requires-Dist: pytest-cov>=4.0.0; extra == "all"
Requires-Dist: mypy>=1.0.0; extra == "all"
Requires-Dist: ruff>=0.1.0; extra == "all"
Requires-Dist: black>=23.0.0; extra == "all"
